nova/__init__.py
nova/novarun.py
nova/core/__init__.py
nova/core/matcher.py
nova/core/parser.py
nova/core/rules.py
nova/core/scanner.py
nova/evaluators/__init__.py
nova/evaluators/base.py
nova/evaluators/condition.py
nova/evaluators/keywords.py
nova/evaluators/llm.py
nova/evaluators/semantics.py
nova/utils/__init__.py
nova/utils/config.py
nova/utils/helpers.py
nova_hunting-0.1.4.dist-info/licenses/LICENCE
nova_hunting-0.1.4.dist-info/METADATA
nova_hunting-0.1.4.dist-info/WHEEL
nova_hunting-0.1.4.dist-info/entry_points.txt
nova_hunting-0.1.4.dist-info/top_level.txt
nova_hunting-0.1.4.dist-info/RECORD
