Metadata-Version: 2.4
Name: nova-hunting
Version: 0.1.4
Summary: Prompt Pattern Matching Framework for Generative AI
Home-page: https://github.com/fr0gger/nova-framework
Author: Thomas Roccia
Author-email: contact@securitybreak.io
License: MIT
Classifier: Programming Language :: Python :: 3
Classifier: License :: OSI Approved :: MIT License
Classifier: Operating System :: OS Independent
Requires-Python: >=3.9
License-File: LICENCE
Requires-Dist: sentence-transformers
Requires-Dist: transformers
Requires-Dist: requests
Requires-Dist: pyyaml
Requires-Dist: colorama
Requires-Dist: openai
Requires-Dist: anthropic
Dynamic: author
Dynamic: author-email
Dynamic: classifier
Dynamic: description
Dynamic: description-content-type
Dynamic: home-page
Dynamic: license
Dynamic: license-file
Dynamic: requires-dist
Dynamic: requires-python
Dynamic: summary
